jurn/__init__.py
jurn/cli.py
jurn/utils.py
jurn-1.0.4.dist-info/LICENSE
jurn-1.0.4.dist-info/METADATA
jurn-1.0.4.dist-info/WHEEL
jurn-1.0.4.dist-info/entry_points.txt
jurn-1.0.4.dist-info/top_level.txt
jurn-1.0.4.dist-info/RECORD
