Metadata-Version: 2.1
Name: jurn
Version: 1.0.4
Summary: A tool for logging work progress throughout the week. Features autocomleting tags and pretty output.
Author-email: Bert Wagner <bertwagner@bertwagner.com>
Project-URL: Homepage, https://github.com/bertwagner/jurn
Classifier: Programming Language :: Python :: 3
Classifier: License :: OSI Approved :: MIT License
Classifier: Operating System :: OS Independent
Requires-Python: >=3.7
License-File: LICENSE
Requires-Dist: Click
Requires-Dist: python-dateutil
